setup.py
antd/__init__.py
antd/ant.py
antd/antfs.py
antd/cfg.py
antd/connect.py
antd/garmin.py
antd/hw.py
antd/main.py
antd/plugin.py
antd/tcx.py
python_ant_downloader.egg-info/PKG-INFO
python_ant_downloader.egg-info/SOURCES.txt
python_ant_downloader.egg-info/dependency_links.txt
python_ant_downloader.egg-info/entry_points.txt
python_ant_downloader.egg-info/requires.txt
python_ant_downloader.egg-info/top_level.txt
test/test_master.py
test/test_slave.py
test/test_wait_for_broadcast.py