Metadata-Version: 1.0
Name: python-ant-downloader
Version: 12.03.21
Summary: Tools for download from wireless Garmin (ANT) GPS devices.
Home-page: https://github.com/braiden/python-ant-downloader
Author: Braiden Kindt
Author-email: braiden@braiden.org
License: BSD
Keywords: ANT Garmin GPS 405 405CX 410
Platform: UNKNOWN
Classifier: Development Status :: 4 - Beta
Classifier: Environment :: Console
Classifier: License :: OSI Approved :: BSD License
